utility.vh
`ifndef __utility_vh__
`define __utility_vh__

`define N 32
`define M 4

`endif

key_expansion.v
`timescale 1ns / 1ps
`include "utility.vh"
module key_expansion #(parameter n=`N, m=`M)(
    input [n*m-1:0] key,
    input [7:0] i, //denotes current round 
    output reg [n-1:0] key_i
);
    localparam [0:61] z_0 = 62'b11111010001001010110000111001101111101000100101011000011100110;
    localparam [0:61] z_1 = 62'b10001110111110010011000010110101000111011111001001100001011010;
    localparam [0:61] z_2 = 62'b10101111011100000011010010011000101000010001111110010110110011;
    localparam [0:61] z_3 = 62'b11011011101011000110010111100000010010001010011100110100001111;
    localparam [0:61] z_4 = 62'b11010001111001101011011000100000010111000011001010010011101111;
    reg [n-1:0] tmp,tmp2, tmp3, ror3, ror1;
    wire [0:61] z;
    reg [7:0] index;
    generate
        assign z = (j(n,m)==0)? z_0:(j(n,m)==1)?z_1:(j(n,m)==2)?z_2:(j(n,m)==3)?z_3:z_4;
    endgenerate
   // assign z = (j(n,m)==0)? z_0:(j(n,m)==1)?z_1:(j(n,m)==2)?z_2:(j(n,m)==3)?z_3:z_4;   
    
    always@(key, i)
    begin
        if(i<m)
            key_i = key[(n*(i+1))-1-:n];
        else
        begin
            tmp =  {key[(n*(m-1))+:3],key[n*m-1-:(n-3)]}; //(key[(n*m-1)-:n] >> 3); Ror 3
            ror3= tmp;
            if (m==4)begin
                tmp2 = tmp ^ key[(2*n)-1-:n];
                tmp = tmp2;
            end
            ror1 = tmp ^ {tmp[0],tmp[n-1:1]}; //(tmp >> 1) ror 1
            tmp=ror1;
            //tmp = tmp ^ {tmp[0],tmp[n-1:1]}; //(tmp >> 1) ror 1
            index = (i-m)<62? i-m: (i-m)-62;
            key_i = ~key[n-1:0] ^ tmp ^ z[index] ^ 2'b11;
        end    
    end

function integer j;
    input integer n;
    input integer m;
    case(n)
        16: j = 0;
        24: j = (m==3)?0:(m==4)?1:-1;
        32: j = (m==3)?2:(m==4)?3:-1;
        48: j = (m==2)?2:(m==3)?3:-1;
        64: j = (m==2)?2:(m==3)?3:(m==4)?4:-1;
        default: j =-1;
     endcase    
endfunction   
endmodule

round.v
`timescale 1ns / 1ps

`include "utility.vh"

module round #(parameter n=`N, m=`M)
    (x, k, y);
    input [(2*n)-1:0] x;
    input [(n-1):0] k;
    output [(2*n)-1:0] y;
    wire [n-1:0] x_0, x_1, rol_1, rol_8, rol_2;
    
    assign x_0 = x[n-1:0];
    assign x_1 = x[(2*n)-1-:n];
    
    assign y[n-1:0] = x_1;
    
    assign rol_1 = {x_1[0+:(n-1)], x_1[n-1]};
    assign rol_2 = {x_1[0+:(n-2)], x_1[n-1-:2]};
    assign rol_8 = {x_1[0+:(n-8)], x_1[n-1-:8]};
    
    assign y[(2*n)-1-:n] = (((rol_1 & rol_8) ^ x_0) ^ rol_2) ^ k;
endmodule

simon.v
`timescale 1ns / 1ps
`include "utility.vh"
module simon #(parameter n=`N, m=`M)
(clk, rst, plaintext, key, ciphertext, en, done);
    input clk, rst, en;
    input [2*n-1:0] plaintext;
    input [n*m-1:0] key;
    output reg [2*n-1:0] ciphertext;
    output done;
    localparam s_idle = 2'b00;
    localparam s_enable = 2'b01;
    localparam s_busy = 2'b10;
    localparam s_done = 2'b11;
    localparam NUM_ROUNDS = T(n,m);
    
    reg [1:0] current_state; 
    wire [1:0] next_state;
    reg [7:0] current_counter;
    wire [7:0] next_counter;
    reg [2*n-1:0] x;
    wire [2*n-1:0] next_x, y;
    wire [n-1:0] k;
    wire [n*m-1:0] key_in;
    wire [n-1:0]key_i;
    reg [n-1:0] key_schedule [NUM_ROUNDS-1:0];
    wire [2*n-1:0] next_ciphertext;
    round #(.n(n),.m(m)) r (.x(x),.y(y),.k(k));
    key_expansion #(.n(n),.m(m)) key_ex(.key(key_in), .i(next_counter), .key_i(key_i));
    reg [7:0] init_counter =0;
    always @(posedge(clk))
    begin
        if (rst) begin
            current_counter <= 8'h00;
            current_state <= s_idle;
            x <= 0;
            ciphertext <= 0;
            for (integer i = 0; i < NUM_ROUNDS; i = i + 1) begin
                key_schedule[i] <= 0;
            end
        end
        else begin
            current_state <= next_state;
            current_counter <= next_counter;
            x <= next_x;
            ciphertext <= next_ciphertext;
            if (current_state == s_enable) begin
                key_schedule[0] <= key[n-1:0];
            end
            else if(current_state == s_busy)
            begin
                key_schedule[next_counter] <= key_i; 
            end
       end
    end
    assign k = (current_counter<m)? key[(current_counter+1)*(n)-1-:n] : key_schedule[current_counter];
    assign key_in = (current_counter <m)? key: {key_schedule[current_counter],key_schedule[current_counter-1],key_schedule[current_counter-2],key_schedule[current_counter-3]};
    assign next_counter = (current_state==s_enable)?0:(current_state===s_busy) ? (current_counter +1) : current_counter; 
    assign next_state = (rst==1)?
                        s_idle:(en==1)?
                        s_enable:(current_state==s_enable)?
                        s_busy:(current_state==s_busy && current_counter<(NUM_ROUNDS-1))?
                        s_busy:(current_state==s_busy && current_counter>=(NUM_ROUNDS-1))?
                        s_done:(current_state==s_done)?s_done:s_idle;
    assign done = (current_state==s_done)?1:0;
    assign next_x = (current_state==s_enable)? plaintext:y;
    assign next_ciphertext = (en==1)? 0: (current_state==s_busy && next_state==s_done) ? y: ciphertext;
    
    //Functions    
    function integer T;
        input integer n;
        input integer m;
        case(n)
            16: T = 32;
            24: T = 36;
            32: T = (m==3)?42:(m==4)?44:-1;
            48: T = (m==2)?52:(m==3)?54:-1;
            64: T = (m==2)?68:(m==3)?69:(m==4)?72:-1;
            default: T =-1;
         endcase        
    endfunction
endmodule

tb_simon.sv
`timescale 1ns / 1ps
module tb_simon;
    // Parameters
    parameter n = 32;  // Half the block size (64/2)
    parameter m = 4;   // Key words (128/32)

    // Inputs
    reg clk;
    reg rst;
    reg en;
    reg [2*n-1:0] plaintext;  // 64-bit plaintext
    reg [n*m-1:0] key;        // 128-bit key

    // Outputs
    wire [2*n-1:0] ciphertext;
    wire done;

    // Instantiate the Unit Under Test (UUT)
    simon #(.n(n), .m(m)) uut (
        .clk(clk), 
        .rst(rst), 
        .plaintext(plaintext), 
        .key(key), 
        .ciphertext(ciphertext), 
        .en(en),
        .done(done)
    );

    // Clock generation
    always begin
        #5 clk = ~clk;
    end

    integer mismatch_count;

    initial begin
        // Initialize inputs
        clk = 0;
        rst = 0;
        en = 0;
        plaintext = 0;
        key = 0;
        mismatch_count = 0;

        // Dump waveform
        $dumpfile("waveform_simon.vcd");
        $dumpvars(0, tb_simon);

        // Reset sequence
        rst = 1;
        #10;
        rst = 0;
        #10;

        // Test 1
        key = 128'h1b1a1918131211100b0a090803020100;
        plaintext = 64'h656b696c20646e75;
        run_test(64'h44c8fc20b9dfa07a);

        // Test 2
        key = 128'h0123456789ABCDEF0123456789ABCDEF;
        plaintext = 64'hFEDCBA9876543210;
        run_test(64'hE0EEA3F009ED2BC7);

        // Test 3
        key = 128'h00112233445566778899AABBCCDDEEFF;
        plaintext = 64'h1234567890ABCDEF;
        run_test(64'h76CBE5E41CB96AF8);

        // Test 4
        key = 128'hAABBCCDDEEFF00112233445566778899;
        plaintext = 64'hDEADBEEFDEADBEEF;
        run_test(64'hFF245021662BA2AF);

        // Test 5
        key = 128'hCAFEBABECAFEBABECAFEBABECAFEBABE;
        plaintext = 64'hCAFEBABECAFEBABE;
        run_test(64'h5DB4EBCDBC6188DE);

        // Recursive Test
        key = 128'hFEDCBA98765432100123456789ABCDEF;
        plaintext = 64'h1234567890ABCDEF;
        run_recursive_test(3, 64'h34BE744934FABB4E, 64'h823A057D5B933604, 64'h06372B3E88230685);

        // Finalize
        if (mismatch_count == 0)
            $display("All tests passed!");
        else
            $display("%0d mismatches out of %0d total tests.", mismatch_count, 6);
        $finish;
    end

    task run_test;
        input [2*n-1:0] expected_ciphertext;
        begin
            // Reset before each test
            rst = 1;
            @(posedge clk);
            rst = 0;
            @(posedge clk);

            // Start encryption
            @(posedge clk);
            en = 1;
            @(posedge clk);
            en = 0;

            // Wait for encryption to complete
            while(done != 1) begin
                @(posedge clk);
            end

            // Check the result
            if (ciphertext !== expected_ciphertext) begin
                $display("Mismatch: Expected Ciphertext = %h, Got = %h", expected_ciphertext, ciphertext);
                mismatch_count = mismatch_count + 1;
            end else begin
                $display("Test passed: Ciphertext = %h", ciphertext);
            end

            // Small delay before next test
            #20;
        end
    endtask

    task run_recursive_test;
        input integer num_iterations;
        input [2*n-1:0] expected_ciphertext1;
        input [2*n-1:0] expected_ciphertext2;
        input [2*n-1:0] expected_ciphertext3;
        reg [2*n-1:0] expected_ciphertexts[2:0];
        integer i;
        begin
            expected_ciphertexts[0] = expected_ciphertext1;
            expected_ciphertexts[1] = expected_ciphertext2;
            expected_ciphertexts[2] = expected_ciphertext3;
            for (i = 0; i < num_iterations; i = i + 1) begin
                // Reset before each iteration
                rst = 1;
                @(posedge clk);
                rst = 0;
                @(posedge clk);

                // Start encryption
                en = 1;
                @(posedge clk);
                en = 0;

                // Wait for encryption to complete
                while(done != 1) begin
                    @(posedge clk);
                end

                // Check the result
                if (ciphertext !== expected_ciphertexts[i]) begin
                    $display("Mismatch in recursive test %0d: Expected Ciphertext = %h, Got = %h", i+1, expected_ciphertexts[i], ciphertext);
                    mismatch_count = mismatch_count + 1;
                end else begin
                    $display("Recursive Test %0d passed: Ciphertext = %h", i+1, ciphertext);
                end

                // Update plaintext with the resultant ciphertext for next iteration
                plaintext = ciphertext;

                // Small delay before next iteration
                #20;
            end
        end
    endtask

endmodule

waveform_simon.vcd
$date
	Mon Jul  1 18:03:11 2024
$end
$version
	Icarus Verilog
$end
$timescale
	1ps
$end
$scope module tb_simon $end
$var wire 1 ! done $end
$var wire 64 " ciphertext [63:0] $end
$var reg 1 # clk $end
$var reg 1 $ en $end
$var reg 128 % key [127:0] $end
$var reg 64 & plaintext [63:0] $end
$var reg 1 ' rst $end
$var integer 32 ( mismatch_count [31:0] $end
$scope module uut $end
$var wire 1 # clk $end
$var wire 1 $ en $end
$var wire 128 ) key [127:0] $end
$var wire 64 * plaintext [63:0] $end
$var wire 1 ' rst $end
$var wire 64 + y [63:0] $end
$var wire 64 , next_x [63:0] $end
$var wire 2 - next_state [1:0] $end
$var wire 8 . next_counter [7:0] $end
$var wire 64 / next_ciphertext [63:0] $end
$var wire 128 0 key_in [127:0] $end
$var wire 32 1 key_i [31:0] $end
$var wire 32 2 k [31:0] $end
$var wire 1 ! done $end
$var reg 64 3 ciphertext [63:0] $end
$var reg 8 4 current_counter [7:0] $end
$var reg 2 5 current_state [1:0] $end
$var reg 8 6 init_counter [7:0] $end
$var reg 64 7 x [63:0] $end
$scope function T $end
$var integer 32 8 m [31:0] $end
$var integer 32 9 n [31:0] $end
$upscope $end
$scope module key_ex $end
$var wire 8 : i [7:0] $end
$var wire 128 ; key [127:0] $end
$var wire 62 < z [0:61] $end
$var reg 8 = index [7:0] $end
$var reg 32 > key_i [31:0] $end
$var reg 32 ? ror1 [31:0] $end
$var reg 32 @ ror3 [31:0] $end
$var reg 32 A tmp [31:0] $end
$var reg 32 B tmp2 [31:0] $end
$scope function j $end
$var integer 32 C m [31:0] $end
$var integer 32 D n [31:0] $end
$upscope $end
$upscope $end
$scope module r $end
$var wire 32 E k [31:0] $end
$var wire 64 F x [63:0] $end
$var wire 64 G y [63:0] $end
$var wire 32 H x_1 [31:0] $end
$var wire 32 I x_0 [31:0] $end
$var wire 32 J rol_8 [31:0] $end
$var wire 32 K rol_2 [31:0] $end
$var wire 32 L rol_1 [31:0] $end
$upscope $end
$scope begin $ivl_for_loop0 $end
$var integer 32 M i [31:0] $end
$upscope $end
$upscope $end
$scope task run_recursive_test $end
$var reg 64 N expected_ciphertext1 [63:0] $end
$var reg 64 O expected_ciphertext2 [63:0] $end
$var reg 64 P expected_ciphertext3 [63:0] $end
$var integer 32 Q i [31:0] $end
$var integer 32 R num_iterations [31:0] $end
$upscope $end
$scope task run_test $end
$var reg 64 S expected_ciphertext [63:0] $end
$upscope $end
$upscope $end
$enddefinitions $end
#0
$dumpvars
bx S
bx R
bx Q
bx P
bx O
bx N
bx M
bx L
bx K
bx J
bx I
bx H
bx G
bx F
bx E
b100000 D
b100 C
bx B
bx A
bx @
bx ?
bx >
bx =
b11011011101011000110010111100000010010001010011100110100001111 <
bx ;
bx :
bx 9
bx 8
bx 7
b0 6
bx 5
bx 4
bx 3
bx 2
bx 1
bx 0
bx /
bx .
b0 -
bx ,
bx +
b0 *
b0 )
b0 (
1'
b0 &
b0 %
0$
0#
bx "
x!
$end
#5000
b0 /
b0 L
b0 K
b0 J
b0 ,
0!
b0 1
b0 >
b0 I
b0 +
b0 G
b0 H
b0 .
b0 :
b0 2
b0 E
b0 0
b0 ;
b0 "
b0 3
b0 7
b0 F
b0 5
b0 4
b101100 M
1#
#10000
0#
0'
#15000
1#
#20000
b1100000010000000010000000000000000000000000000000000000000 ,
b1100000010000000010000000000000000000000000000000000000000 +
b1100000010000000010000000000000000000000000000000000000000 G
b11000000100000000100000000 1
b11000000100000000100000000 >
b11000000100000000100000000 2
b11000000100000000100000000 E
b11011000110100001100100011000000100110001001000010001000100000000101100001010000010010000100000000011000000100000000100000000 0
b11011000110100001100100011000000100110001001000010001000100000000101100001010000010010000100000000011000000100000000100000000 ;
0#
1'
b100010011001000111111000010000010111001110111111010000001111010 S
b110010101101011011010010110110000100000011001000110111001110101 &
b110010101101011011010010110110000100000011001000110111001110101 *
b11011000110100001100100011000000100110001001000010001000100000000101100001010000010010000100000000011000000100000000100000000 %
b11011000110100001100100011000000100110001001000010001000100000000101100001010000010010000100000000011000000100000000100000000 )
#25000
b110000001000000001000000000 L
b1100000010000000010000000000 K
b10000000010000000000000011 J
b110100001010000001010000000000000011000000100000000100000000 ,
b110100001010000001010000000000000011000000100000000100000000 +
b110100001010000001010000000000000011000000100000000100000000 G
b11000000100000000100000000 H
b1100000010000000010000000000000000000000000000000000000000 7
b1100000010000000010000000000000000000000000000000000000000 F
0'
1#
#30000
0#
#35000
b11010000101000000101000000000 L
b110100001010000001010000000000 K
b1010000001010000000000001101 J
b11111000101100000101000000000000001101000010100000010100000000 ,
b11000000100000000100000000 I
b11111000101100000101000000000000001101000010100000010100000000 +
b11111000101100000101000000000000001101000010100000010100000000 G
b1101000010100000010100000000 H
b110100001010000001010000000000000011000000100000000100000000 7
b110100001010000001010000000000000011000000100000000100000000 F
1#
#40000
0#
#45000
b1111100010110000010100000000000 L
b11111000101100000101000000000000 K
b101100000101000000000000111110 J
b1101101010101000010101000000000000111110001011000001010000000000 ,
b1101000010100000010100000000 I
b1101101010101000010101000000000000111110001011000001010000000000 +
b1101101010101000010101000000000000111110001011000001010000000000 G
b111110001011000001010000000000 H
b11111000101100000101000000000000001101000010100000010100000000 7
b11111000101100000101000000000000001101000010100000010100000000 F
b1 -
1$
1#
#50000
0#
#55000
b10110101010100001010100000000001 L
b1101010101000010101000000000011 K
b10101000010101000000000011011010 J
b111110001011000001010000000000 I
b1111011111011111010001010000001111011010101010000101010000000000 +
b1111011111011111010001010000001111011010101010000101010000000000 G
b11011010101010000101010000000000 H
b110010101101011011010010110110000100000011001000110111001110101 ,
b1101101010101000010101000000000000111110001011000001010000000000 7
b1101101010101000010101000000000000111110001011000001010000000000 F
b1 5
b10 -
0$
1#
#60000
0#
#65000
b10 -
b11001010110101101101001011011000 L
b10010101101011011010010110110001 K
b1101011011010010110110001100101 J
b1011000010100000100100001000 1
b1011000010100000100100001000 >
b100000011001000110111001110101 I
b1111110010001011100010101000010001100101011010110110100101101100 +
b1111110010001011100010101000010001100101011010110110100101101100 G
b1100101011010110110100101101100 H
b1 .
b1 :
b1111110010001011100010101000010001100101011010110110100101101100 ,
b110010101101011011010010110110000100000011001000110111001110101 7
b110010101101011011010010110110000100000011001000110111001110101 F
b10 5
1#
#70000
0#
#75000
b10011000100100001000100010000 1
b10011000100100001000100010000 >
b11111001000101110001010100001001 L
b11110010001011100010101000010011 K
b10001011100010101000010011111100 J
b1010101001101010011100111111111111100100010111000101010000100 ,
b10 .
b10 :
b1100101011010110110100101101100 I
b1010101001101010011100111111111111100100010111000101010000100 +
b1010101001101010011100111111111111100100010111000101010000100 G
b11111100100010111000101010000100 H
b1011000010100000100100001000 2
b1011000010100000100100001000 E
b1111110010001011100010101000010001100101011010110110100101101100 7
b1111110010001011100010101000010001100101011010110110100101101100 F
b1 4
1#
#80000
0#
#85000
b11011000110100001100100011000 1
b11011000110100001100100011000 >
b101010100110101001110011111110 L
b1010101001101010011100111111100 K
b1001101010011100111111100010101 J
b1011001010100110101111100111110000010101010011010100111001111111 ,
b11 .
b11 :
b11111100100010111000101010000100 I
b1011001010100110101111100111110000010101010011010100111001111111 +
b1011001010100110101111100111110000010101010011010100111001111111 G
b10101010011010100111001111111 H
b10011000100100001000100010000 2
b10011000100100001000100010000 E
b1010101001101010011100111111111111100100010111000101010000100 7
b1010101001101010011100111111111111100100010111000101010000100 F
b10 4
1#
#90000
0#
#95000
b1110000101000000001000111000011 1
b1110000101000000001000111000011 >
b0 =
b10001100010111011110111100111110 ?
b1000011010010100101000101011 B
b11011000110100001100100011 @
b10001100010111011110111100111110 A
b1100101010011010111110011111001 L
b11001010100110101111100111110010 K
b10100110101111100111110010110010 J
b1110000011000001110100100010010110110010101001101011111001111100 ,
b100 .
b100 :
b10101010011010100111001111111 I
b1110000011000001110100100010010110110010101001101011111001111100 +
b1110000011000001110100100010010110110010101001101011111001111100 G
b10110010101001101011111001111100 H
b11011000110100001100100011000 2
b11011000110100001100100011000 E
b1011001010100110101111100111110000010101010011010100111001111111 7
b1011001010100110101111100111110000010101010011010100111001111111 F
b11 4
1#
#100000
0#
#105000
b11000001100000111010010001001011 L
b10000011000001110100100010010111 K
b11000001110100100010010111100000 J
b1000000010000011110000110110100011100000110000011101001000100101 ,
b10110111011100001110110001001001 1
b10110111011100001110110001001001 >
b1 =
b1000011100001010001101010111100 ?
b1111101000001100001001100101000 B
b1101110000101000000001000111000 @
b1000011100001010001101010111100 A
b101 .
b101 :
b10110010101001101011111001111100 I
b1000000010000011110000110110100011100000110000011101001000100101 +
b1000000010000011110000110110100011100000110000011101001000100101 G
b11100000110000011101001000100101 H
b1110000101000000001000111000011 2
b1110000101000000001000111000011 E
b1110000101000000001000111000011000110110001101000011001000110000001001100010010000100010001000000001011000010100000100100001000 0
b1110000101000000001000111000011000110110001101000011001000110000001001100010010000100010001000000001011000010100000100100001000 ;
b1110000011000001110100100010010110110010101001101011111001111100 7
b1110000011000001110100100010010110110010101001101011111001111100 F
b100 4
1#
#110000
0#
#115000
b1000001111000011011010001 L
b10000011110000110110100010 K
b10000011110000110110100010000000 J
b101010010111101001100110100111010000000100000111100001101101000 ,
b1010111111000111110100000110101 1
b1010111111000111110100000110101 >
b10 =
b10111011000011100000011011011001 ?
b101101111101000000010010010001 B
b110110111011100001110110001001 @
b10111011000011100000011011011001 A
b110 .
b110 :
b11100000110000011101001000100101 I
b101010010111101001100110100111010000000100000111100001101101000 +
b101010010111101001100110100111010000000100000111100001101101000 G
b10000000100000111100001101101000 H
b10110111011100001110110001001001 2
b10110111011100001110110001001001 E
b10110111011100001110110001001001011100001010000000010001110000110001101100011010000110010001100000010011000100100001000100010000 0
b10110111011100001110110001001001011100001010000000010001110000110001101100011010000110010001100000010011000100100001000100010000 ;
b1000000010000011110000110110100011100000110000011101001000100101 7
b1000000010000011110000110110100011100000110000011101001000100101 F
b101 4
1#
#120000
0#
#125000
b10101001011110100110011010011100 L
b1010010111101001100110100111001 K
b10111101001100110100111001010100 J
b10110010100110101000000111000001010100101111010011001101001110 ,
b11010011100101111011110001000010 1
b11010011100101111011110001000010 >
b11 =
b110111011100100101101010100111 ?
b11011010010111000110110011000101 B
b10101010111111000111110100000110 @
b110111011100100101101010100111 A
b111 .
b111 :
b10000000100000111100001101101000 I
b10110010100110101000000111000001010100101111010011001101001110 +
b10110010100110101000000111000001010100101111010011001101001110 G
b1010100101111010011001101001110 H
b1010111111000111110100000110101 2
b1010111111000111110100000110101 E
b1010111111000111110100000110101101101110111000011101100010010010111000010100000000100011100001100011011000110100001100100011000 0
b1010111111000111110100000110101101101110111000011101100010010010111000010100000000100011100001100011011000110100001100100011000 ;
b101010010111101001100110100111010000000100000111100001101101000 7
b101010010111101001100110100111010000000100000111100001101101000 F
b110 4
1#
#130000
0#
#135000
b1011001010011010100000011100000 L
b10110010100110101000000111000000 K
b10100110101000000111000000101100 J
b11010110110000010011101110110000101100101001101010000001110000 ,
b10010100110111001111100000011111 1
b10010100110111001111100000011111 >
b100 =
b11011100000110001011000100001 ?
b11101101000000100001101111000001 B
b1011010011100101111011110001000 @
b11011100000110001011000100001 A
b1000 .
b1000 :
b1010100101111010011001101001110 I
b11010110110000010011101110110000101100101001101010000001110000 +
b11010110110000010011101110110000101100101001101010000001110000 G
b101100101001101010000001110000 H
b11010011100101111011110001000010 2
b11010011100101111011110001000010 E
b11010011100101111011110001000010010101111110001111101000001101011011011101110000111011000100100101110000101000000001000111000011 0
b11010011100101111011110001000010010101111110001111101000001101011011011101110000111011000100100101110000101000000001000111000011 ;
b10110010100110101000000111000001010100101111010011001101001110 7
b10110010100110101000000111000001010100101111010011001101001110 F
b111 4
1#
#140000
0#
#145000
b1101011011000001001110111011000 L
b11010110110000010011101110110000 K
b10110000010011101110110000110101 J
b100111011111011111011111100111100110101101100000100111011101100 ,
b10111111010010110101111100011000 1
b10111111010010110101111100011000 >
b101 =
b11110111110001000100110010101101 ?
b10100101011110000111011100110110 B
b11110010100110111001111100000011 @
b11110111110001000100110010101101 A
b1001 .
b1001 :
b101100101001101010000001110000 I
b100111011111011111011111100111100110101101100000100111011101100 +
b100111011111011111011111100111100110101101100000100111011101100 G
b110101101100000100111011101100 H
b10010100110111001111100000011111 2
b10010100110111001111100000011111 E
b10010100110111001111100000011111110100111001011110111100010000100101011111100011111010000011010110110111011100001110110001001001 0
b10010100110111001111100000011111110100111001011110111100010000100101011111100011111010000011010110110111011100001110110001001001 ;
b11010110110000010011101110110000101100101001101010000001110000 7
b11010110110000010011101110110000101100101001101010000001110000 F
b1000 4
1#
#150000
0#
#155000
b10011101111101111101111110011110 L
b111011111011111011111100111101 K
b11111011111011111100111101001110 J
b10100011110011011000011100011101001110111110111110111111001111 ,
b10001110010111011010101110111001 1
b10001110010111011010101110111001 >
b110 =
b100110010000011011110001110001 ?
b11000100011111101101011110100001 B
b10111111010010110101111100011 @
b100110010000011011110001110001 A
b1010 .
b1010 :
b110101101100000100111011101100 I
b10100011110011011000011100011101001110111110111110111111001111 +
b10100011110011011000011100011101001110111110111110111111001111 G
b1001110111110111110111111001111 H
b10111111010010110101111100011000 2
b10111111010010110101111100011000 E
b10111111010010110101111100011000100101001101110011111000000111111101001110010111101111000100001001010111111000111110100000110101 0
b10111111010010110101111100011000100101001101110011111000000111111101001110010111101111000100001001010111111000111110100000110101 ;
b100111011111011111011111100111100110101101100000100111011101100 7
b100111011111011111011111100111100110101101100000100111011101100 F
b1001 4
1#
#160000
0#
#165000
b1010001111001101100001110001110 L
b10100011110011011000011100011100 K
b11110011011000011100011100101000 J
b11001000001011000000000110001000101000111100110110000111000111 ,
b11011011111101001010100001100011 1
b11011011111101001010100001100011 >
b111 =
b11110111100111001110101111011100 ?
b10100101000101110100110101101000 B
b110001110010111011010101110111 @
b11110111100111001110101111011100 A
b1011 .
b1011 :
b1001110111110111110111111001111 I
b11001000001011000000000110001000101000111100110110000111000111 +
b11001000001011000000000110001000101000111100110110000111000111 G
b101000111100110110000111000111 H
b10001110010111011010101110111001 2
b10001110010111011010101110111001 E
b10001110010111011010101110111001101111110100101101011111000110001001010011011100111110000001111111010011100101111011110001000010 0
b10001110010111011010101110111001101111110100101101011111000110001001010011011100111110000001111111010011100101111011110001000010 ;
b10100011110011011000011100011101001110111110111110111111001111 7
b10100011110011011000011100011101001110111110111110111111001111 F
b1010 4
1#
#170000
0#
#175000
b1100100000101100000000011000100 L
b11001000001011000000000110001000 K
b1011000000000110001000110010 J
b11101100101011110010000010110000110010000010110000000001100010 ,
b11001101000011000010100011111100 1
b11001101000011000010100011111100 >
b1000 =
b10100110001011110010111100011110 ?
b11000100001101011100101000010100 B
b1111011011111101001010100001100 @
b10100110001011110010111100011110 A
b1100 .
b1100 :
b101000111100110110000111000111 I
b11101100101011110010000010110000110010000010110000000001100010 +
b11101100101011110010000010110000110010000010110000000001100010 G
b110010000010110000000001100010 H
b11011011111101001010100001100011 2
b11011011111101001010100001100011 E
b11011011111101001010100001100011100011100101110110101011101110011011111101001011010111110001100010010100110111001111100000011111 0
b11011011111101001010100001100011100011100101110110101011101110011011111101001011010111110001100010010100110111001111100000011111 ;
b11001000001011000000000110001000101000111100110110000111000111 7
b11001000001011000000000110001000101000111100110110000111000111 F
b1011 4
1#
#180000
0#
#185000
b1110110010101111001000001011000 L
b11101100101011110010000010110000 K
b101011110010000010110000111011 J
b11000111101000000010000011011000111011001010111100100000101100 ,
b1011100101101101001100100010001 1
b1011100101101101001100100010001 >
b1001 =
b11100000000100011100111110101 ?
b10111111111000010111010100110 B
b10011001101000011000010100011111 @
b11100000000100011100111110101 A
b1101 .
b1101 :
b110010000010110000000001100010 I
b11000111101000000010000011011000111011001010111100100000101100 +
b11000111101000000010000011011000111011001010111100100000101100 G
b111011001010111100100000101100 H
b11001101000011000010100011111100 2
b11001101000011000010100011111100 E
b11001101000011000010100011111100110110111111010010101000011000111000111001011101101010111011100110111111010010110101111100011000 0
b11001101000011000010100011111100110110111111010010101000011000111000111001011101101010111011100110111111010010110101111100011000 ;
b11101100101011110010000010110000110010000010110000000001100010 7
b11101100101011110010000010110000110010000010110000000001100010 F
b1100 4
1#
#190000
0#
#195000
b1100011110100000001000001101100 L
b11000111101000000010000011011000 K
b11101000000010000011011000110001 J
b1100000000111101011000011100010100110001111010000000100000110110 ,
b1111001111100010001001010100101 1
b1111001111100010001001010100101 >
b1010 =
b1000010100110100011011100001 ?
b11110000011000100111101101000001 B
b101011100101101101001100100010 @
b1000010100110100011011100001 A
b1110 .
b1110 :
b111011001010111100100000101100 I
b1100000000111101011000011100010100110001111010000000100000110110 +
b1100000000111101011000011100010100110001111010000000100000110110 G
b110001111010000000100000110110 H
b1011100101101101001100100010001 2
b1011100101101101001100100010001 E
b1011100101101101001100100010001110011010000110000101000111111001101101111110100101010000110001110001110010111011010101110111001 0
b1011100101101101001100100010001110011010000110000101000111111001101101111110100101010000110001110001110010111011010101110111001 ;
b11000111101000000010000011011000111011001010111100100000101100 7
b11000111101000000010000011011000111011001010111100100000101100 F
b1101 4
1#
#200000
0#
#205000
b10000000011110101100001110001011 L
b111101011000011100010111 K
b111101011000011100010111000000 J
b100100010001100010111000000010011000000001111010110000111000101 ,
b1110111001000000101100001100011 1
b1110111001000000101100001100011 >
b1011 =
b1010011001010110000111111111100 ?
b1100010001100100000101010101000 B
b10101111001111100010001001010100 @
b1010011001010110000111111111100 A
b1111 .
b1111 :
b110001111010000000100000110110 I
b100100010001100010111000000010011000000001111010110000111000101 +
b100100010001100010111000000010011000000001111010110000111000101 G
b11000000001111010110000111000101 H
b1111001111100010001001010100101 2
b1111001111100010001001010100101 E
b1111001111100010001001010100101010111001011011010011001000100011100110100001100001010001111110011011011111101001010100001100011 0
b1111001111100010001001010100101010111001011011010011001000100011100110100001100001010001111110011011011111101001010100001100011 ;
b1100000000111101011000011100010100110001111010000000100000110110 7
b1100000000111101011000011100010100110001111010000000100000110110 F
b1110 4
1#
#210000
0#
#215000
b10010001000110001011100000001000 L
b100010001100010111000000010001 K
b10001100010111000000010001001000 J
b1010100110100010010011011111101001000100011000101110000000100 ,
b10011001100010000000110000010010 1
b10011001100010000000110000010010 >
b1100 =
b10101011011110111101101100010011 ?
b110010010100101001001000011101 B
b1101110111001000000101100001100 @
b10101011011110111101101100010011 A
b10000 .
b10000 :
b11000000001111010110000111000101 I
b1010100110100010010011011111101001000100011000101110000000100 +
b1010100110100010010011011111101001000100011000101110000000100 G
b1001000100011000101110000000100 H
b1110111001000000101100001100011 2
b1110111001000000101100001100011 E
b1110111001000000101100001100011011110011111000100010010101001010101110010110110100110010001000111001101000011000010100011111100 0
b1110111001000000101100001100011011110011111000100010010101001010101110010110110100110010001000111001101000011000010100011111100 ;
b100100010001100010111000000010011000000001111010110000111000101 7
b100100010001100010111000000010011000000001111010110000111000101 F
b1111 4
1#
#220000
0#
#225000
b101010011010001001001101111110 L
b1010100110100010010011011111100 K
b110100010010011011111100010101 J
b1010010110011101111001011111111000010101001101000100100110111111 ,
b11100111010010111110001011000 1
b11100111010010111110001011000 >
b1101 =
b10111111101000000001101010110100 ?
b101010110000000001001100100111 B
b1010011001100010000000110000010 @
b10111111101000000001101010110100 A
b10001 .
b10001 :
b1001000100011000101110000000100 I
b1010010110011101111001011111111000010101001101000100100110111111 +
b1010010110011101111001011111111000010101001101000100100110111111 G
b10101001101000100100110111111 H
b10011001100010000000110000010010 2
b10011001100010000000110000010010 E
b10011001100010000000110000010010011101110010000001011000011000110111100111110001000100101010010101011100101101101001100100010001 0
b10011001100010000000110000010010011101110010000001011000011000110111100111110001000100101010010101011100101101101001100100010001 ;
b1010100110100010010011011111101001000100011000101110000000100 7
b1010100110100010010011011111101001000100011000101110000000100 F
b10000 4
1#
#230000
0#
